odoo/addons/stock_picking_batch_creation/README.rst
odoo/addons/stock_picking_batch_creation/__init__.py
odoo/addons/stock_picking_batch_creation/__manifest__.py
odoo/addons/stock_picking_batch_creation/exceptions.py
odoo/addons/stock_picking_batch_creation/hooks.py
odoo/addons/stock_picking_batch_creation/i18n/fr.po
odoo/addons/stock_picking_batch_creation/i18n/it.po
odoo/addons/stock_picking_batch_creation/i18n/stock_picking_batch_creation.pot
odoo/addons/stock_picking_batch_creation/models/__init__.py
odoo/addons/stock_picking_batch_creation/models/stock_device_type.py
odoo/addons/stock_picking_batch_creation/models/stock_picking.py
odoo/addons/stock_picking_batch_creation/models/stock_picking_batch.py
odoo/addons/stock_picking_batch_creation/readme/CONTRIBUTORS.md
odoo/addons/stock_picking_batch_creation/readme/CREDITS.md
odoo/addons/stock_picking_batch_creation/readme/DESCRIPTION.md
odoo/addons/stock_picking_batch_creation/readme/USAGE.md
odoo/addons/stock_picking_batch_creation/security/ir.model.access.csv
odoo/addons/stock_picking_batch_creation/static/description/icon.png
odoo/addons/stock_picking_batch_creation/static/description/index.html
odoo/addons/stock_picking_batch_creation/static/src/js/error.esm.js
odoo/addons/stock_picking_batch_creation/tests/__init__.py
odoo/addons/stock_picking_batch_creation/tests/common.py
odoo/addons/stock_picking_batch_creation/tests/test_batch_creation_splitting.py
odoo/addons/stock_picking_batch_creation/tests/test_clustering_conditions.py
odoo/addons/stock_picking_batch_creation/tests/test_get_device_to_use.py
odoo/addons/stock_picking_batch_creation/tests/test_picking_lock.py
odoo/addons/stock_picking_batch_creation/views/stock_device_type.xml
odoo/addons/stock_picking_batch_creation/views/stock_picking.xml
odoo/addons/stock_picking_batch_creation/views/stock_picking_batch.xml
odoo/addons/stock_picking_batch_creation/wizards/__init__.py
odoo/addons/stock_picking_batch_creation/wizards/make_picking_batch.py
odoo_addon_stock_picking_batch_creation-18.0.1.4.0.dist-info/METADATA
odoo_addon_stock_picking_batch_creation-18.0.1.4.0.dist-info/WHEEL
odoo_addon_stock_picking_batch_creation-18.0.1.4.0.dist-info/top_level.txt
odoo_addon_stock_picking_batch_creation-18.0.1.4.0.dist-info/RECORD
