Metadata-Version: 2.1
Name: odoo-addon-stock_picking_batch_creation
Version: 18.0.1.4.0
Requires-Python: >=3.10
Requires-Dist: odoo-addon-stock_picking_volume==18.0.*
Requires-Dist: odoo-addon-stock_split_picking_dimension==18.0.*
Requires-Dist: odoo==18.0.*
Summary: Create a batch of pickings to be processed all together
Home-page: https://github.com/OCA/stock-logistics-workflow
License: AGPL-3
Author: ACSONE SA/NV,BCIM,Odoo Community Association (OCA)
Author-email: support@odoo-community.org
Classifier: Programming Language :: Python
Classifier: Framework :: Odoo
Classifier: Framework :: Odoo :: 18.0
Classifier: License :: OSI Approved :: GNU Affero General Public License v3
Classifier: Development Status :: 4 - Beta
